plann/__init__.py
plann/cli.py
plann/commands.py
plann/config.py
plann/interactive.py
plann/lib.py
plann/metadata.py
plann/panic_planning.py
plann/template.py
plann/timespec.py
plann-1.0.0.dist-info/LICENSE.TXT
plann-1.0.0.dist-info/METADATA
plann-1.0.0.dist-info/WHEEL
plann-1.0.0.dist-info/entry_points.txt
plann-1.0.0.dist-info/top_level.txt
plann-1.0.0.dist-info/RECORD
